AUTHORS
LICENSE
MANIFEST.in
README.rst
requirements-test.txt
requirements.txt
setup.py
watson/__init__.py
watson/cache/__init__.py
watson/cache/decorators.py
watson/cache/storage.py
watson_cache.egg-info/PKG-INFO
watson_cache.egg-info/SOURCES.txt
watson_cache.egg-info/dependency_links.txt
watson_cache.egg-info/not-zip-safe
watson_cache.egg-info/requires.txt
watson_cache.egg-info/top_level.txt