Metadata-Version: 1.1
Name: watson-cache
Version: 1.0.0
Summary: Caching strategies for the web.
Home-page: http://github.com/watsonpy/watson-cache
Author: Simon Coulton
Author-email: simon at bespohk.com
License: Copyright (c) 2012-2014 Bespohk, and is maintained by multiple
